GDmicro/GDmicro.py
GDmicro/GDmicro_preprocess.py
GDmicro/__init__.py
GDmicro/allmeta.tsv
GDmicro/build_graph_given_matrix_with_knn.py
GDmicro/build_graph_given_matrix_with_knn_train_mode.py
GDmicro/build_graph_with_embedding.py
GDmicro/build_graph_with_embedding_train_mode.py
GDmicro/calculate_avg_acc_of_cross_validation_test.py
GDmicro/calculate_avg_acc_of_cross_validation_train_mode.py
GDmicro/check_neighbor_label.py
GDmicro/feature_select_model.R
GDmicro/feature_select_model_nodirect.R
GDmicro/gcn_model.py
GDmicro/gcn_model_train_mode.py
GDmicro/merge_embedding_vector.py
GDmicro/merge_embedding_vector_train_mode.py
GDmicro/mmd.py
GDmicro/norm_features.R
GDmicro/parameters.yaml
GDmicro/preprocess_matrix_pca.py
GDmicro/run_GCN_train_mode.py
GDmicro/run_MLP_embedding.py
GDmicro/run_MLP_embedding_da.py
GDmicro/run_MLP_embedding_da_for_node.py
GDmicro/run_MLP_embedding_train_mode.py
GDmicro/trans_embedding_vector.py
GDmicro/transform_matrix_anno.py
GDmicro/higra/__init__.py
GDmicro/higra/concept.py
GDmicro/higra/data_cache.py
GDmicro/higra/hg_utils.py
GDmicro/higra/higram.cpython-37m-x86_64-linux-gnu.so
GDmicro/higra/sorting.py
GDmicro/higra/__pycache__/__init__.cpython-37.pyc
GDmicro/higra/__pycache__/concept.cpython-37.pyc
GDmicro/higra/__pycache__/data_cache.cpython-37.pyc
GDmicro/higra/__pycache__/hg_utils.cpython-37.pyc
GDmicro/higra/__pycache__/sorting.cpython-37.pyc
GDmicro/higra/accumulator/__init__.py
GDmicro/higra/accumulator/at_accumulator.py
GDmicro/higra/accumulator/graph_accumulator.py
GDmicro/higra/accumulator/tree_accumulator.py
GDmicro/higra/accumulator/tree_contour_accumulator.py
GDmicro/higra/accumulator/__pycache__/__init__.cpython-37.pyc
GDmicro/higra/accumulator/__pycache__/at_accumulator.cpython-37.pyc
GDmicro/higra/accumulator/__pycache__/graph_accumulator.cpython-37.pyc
GDmicro/higra/accumulator/__pycache__/tree_accumulator.cpython-37.pyc
GDmicro/higra/accumulator/__pycache__/tree_contour_accumulator.cpython-37.pyc
gdmicro-1.0.10.dist-info/METADATA
gdmicro-1.0.10.dist-info/WHEEL
gdmicro-1.0.10.dist-info/entry_points.txt
gdmicro-1.0.10.dist-info/top_level.txt
gdmicro-1.0.10.dist-info/zip-safe
gdmicro-1.0.10.dist-info/RECORD
